[
    {
        "fileName":"1.jpg",
        "title":"几米的猜想",
        "desc":"《李米的猜想》是华谊兄弟、骄阳电影有限公司联合出品的一部悬疑爱情片，由曹保平执导，周迅、邓超、张涵予、王宝强等主演。2008年9月19日，该片在中国内地上映。影片讲述了一个名叫李米的出租车司机，四年来不顾一切寻觅失踪男友的故事。2009年，该片获得第二届铁象电影大赏十佳电影、上海影评人奖十佳电影等奖项；周迅也凭借此片获得了第27届中国电影金鸡奖最佳女主角奖、第16届北京大学生电影节最佳女主角等奖项。"
    },
    {
        "fileName":"2.jpg",
        "title":"几米的猜想",
        "desc":"几米的故事"
    },
    {
        "fileName":"3.jpg",
        "title":"几米的猜想",
        "desc":"几米的故事"
    },
    {
        "fileName":"4.jpg",
        "title":"几米的猜想",
        "desc":"几米的故事"
    },
    {
        "fileName":"5.jpg",
        "title":"几米的猜想",
        "desc":"几米的故事"
    },
    {
        "fileName":"6.jpg",
        "title":"几米的猜想",
        "desc":"几米的故事"
    },
    {
        "fileName":"7.jpg",
        "title":"几米的猜想",
        "desc":"几米的故事"
    },
    {
        "fileName":"8.jpg",
        "title":"几米的猜想",
        "desc":"几米的故事"
    },
    {
        "fileName":"9.jpg",
        "title":"几米的猜想",
        "desc":"几米的故事"
    },
    {
        "fileName":"10.jpg",
        "title":"几米的猜想",
        "desc":"几米的故事"
    },
    {
        "fileName":"11.jpg",
        "title":"几米的猜想",
        "desc":"几米的故事"
    },
    {
        "fileName":"12.jpg",
        "title":"几米的猜想",
        "desc":"几米的故事"
    },
    {
        "fileName":"13.jpg",
        "title":"几米的猜想",
        "desc":"几米的故事"
    },
    {
        "fileName":"14.jpg",
        "title":"几米的猜想",
        "desc":"几米的故事"
    },
    {
        "fileName":"15.jpg",
        "title":"几米的猜想",
        "desc":"几米的故事"
    },
    {
        "fileName":"16.jpg",
        "title":"几米的猜想",
        "desc":"几米的故事"
    },
    {
        "fileName":"17.jpg",
        "title":"几米的猜想",
        "desc":"几米的故事"
    },
    {
        "fileName":"18.jpg",
        "title":"几米的猜想",
        "desc":"几米的故事"
    }
]
